PyFlint-0.1.dist-info/DESCRIPTION.rst
PyFlint-0.1.dist-info/METADATA
PyFlint-0.1.dist-info/RECORD
PyFlint-0.1.dist-info/WHEEL
PyFlint-0.1.dist-info/metadata.json
PyFlint-0.1.dist-info/top_level.txt
pyflint/__init__.py
